runit/__init__.py
runit/runit.py
runit_parallel-0.0.3.dist-info/METADATA
runit_parallel-0.0.3.dist-info/WHEEL
runit_parallel-0.0.3.dist-info/entry_points.txt
runit_parallel-0.0.3.dist-info/top_level.txt
runit_parallel-0.0.3.dist-info/RECORD
