Metadata-Version: 2.1
Name: runit-parallel
Version: 0.0.3
Summary: runit: scheduling multiple commands with limited devices
Author: Kitsunetic
Author-email: jh.shim.gg@gmail.com
